odoo/addons/mail_cc_and_to_text/README.rst
odoo/addons/mail_cc_and_to_text/__init__.py
odoo/addons/mail_cc_and_to_text/__manifest__.py
odoo/addons/mail_cc_and_to_text/models/__init__.py
odoo/addons/mail_cc_and_to_text/models/mail_mail.py
odoo/addons/mail_cc_and_to_text/models/mail_message.py
odoo/addons/mail_cc_and_to_text/models/mail_thread.py
odoo/addons/mail_cc_and_to_text/static/description/icon.png
odoo/addons/mail_cc_and_to_text/wizard/__init__.py
odoo/addons/mail_cc_and_to_text/wizard/mail_compose_message.py
odoo/addons/mail_cc_and_to_text/wizard/mail_compose_message_view.xml
odoo12_addon_mail_cc_and_to_text-12.0.0.1.0.dist-info/METADATA
odoo12_addon_mail_cc_and_to_text-12.0.0.1.0.dist-info/WHEEL
odoo12_addon_mail_cc_and_to_text-12.0.0.1.0.dist-info/top_level.txt
odoo12_addon_mail_cc_and_to_text-12.0.0.1.0.dist-info/RECORD
